sphinxcontrib/oembed.py
sphinxcontrib_oembed-0.2.2.dist-info/LICENSE
sphinxcontrib_oembed-0.2.2.dist-info/WHEEL
sphinxcontrib_oembed-0.2.2.dist-info/METADATA
sphinxcontrib_oembed-0.2.2.dist-info/RECORD
