Metadata-Version: 2.1
Name: sphinxcontrib-oembed
Version: 0.2.2
Summary: Embed HTML content by URL from eEmbed consumer
Author-email: Kazuya Takei <myself@attakei.net>
Classifier: Development Status :: 7 - Inactive
Classifier: Framework :: Sphinx
Classifier: Framework :: Sphinx :: Extension
Classifier: Intended Audience :: Developers
Classifier: License :: OSI Approved :: Apache Software License
Classifier: Programming Language :: Python :: 3.7
Classifier: Programming Language :: Python :: 3.8
Classifier: Programming Language :: Python :: 3.9
Classifier: Programming Language :: Python :: 3.10
Classifier: Topic :: Documentation :: Sphinx
Requires-Dist: Sphinx
Requires-Dist: requests
Requires-Dist: black >=22.3.0,<23 ; extra == "test"
Requires-Dist: pytest >=7.1.1,<8 ; extra == "test"
Project-URL: Home, https://github.com/attakei-lab/sphinxcontrib-oembed/
Provides-Extra: test
